cptac/__init__.py
cptac/exceptions.py
cptac/version.py
cptac/cancers/__init__.py
cptac/cancers/brca.py
cptac/cancers/cancer.py
cptac/cancers/ccrcc.py
cptac/cancers/coad.py
cptac/cancers/gbm.py
cptac/cancers/hnscc.py
cptac/cancers/lscc.py
cptac/cancers/luad.py
cptac/cancers/ov.py
cptac/cancers/pdac.py
cptac/cancers/source.py
cptac/cancers/ucec.py
cptac/cancers/bcm/__init__.py
cptac/cancers/bcm/bcmbrca.py
cptac/cancers/bcm/bcmccrcc.py
cptac/cancers/bcm/bcmcoad.py
cptac/cancers/bcm/bcmgbm.py
cptac/cancers/bcm/bcmhnscc.py
cptac/cancers/bcm/bcmlscc.py
cptac/cancers/bcm/bcmluad.py
cptac/cancers/bcm/bcmov.py
cptac/cancers/bcm/bcmpdac.py
cptac/cancers/bcm/bcmucec.py
cptac/cancers/broad/__init__.py
cptac/cancers/broad/broadbrca.py
cptac/cancers/broad/broadccrcc.py
cptac/cancers/broad/broadcoad.py
cptac/cancers/broad/broadgbm.py
cptac/cancers/broad/broadhnscc.py
cptac/cancers/broad/broadlscc.py
cptac/cancers/broad/broadluad.py
cptac/cancers/broad/broadov.py
cptac/cancers/broad/broadpdac.py
cptac/cancers/broad/broaducec.py
cptac/cancers/harmonized/__init__.py
cptac/cancers/harmonized/harmonized.py
cptac/cancers/mssm/__init__.py
cptac/cancers/mssm/mssm.py
cptac/cancers/umich/__init__.py
cptac/cancers/umich/umichbrca.py
cptac/cancers/umich/umichccrcc.py
cptac/cancers/umich/umichcoad.py
cptac/cancers/umich/umichgbm.py
cptac/cancers/umich/umichhnscc.py
cptac/cancers/umich/umichlscc.py
cptac/cancers/umich/umichluad.py
cptac/cancers/umich/umichov.py
cptac/cancers/umich/umichpdac.py
cptac/cancers/umich/umichucec.py
cptac/cancers/washu/__init__.py
cptac/cancers/washu/washubrca.py
cptac/cancers/washu/washuccrcc.py
cptac/cancers/washu/washucoad.py
cptac/cancers/washu/washugbm.py
cptac/cancers/washu/washuhnscc.py
cptac/cancers/washu/washulscc.py
cptac/cancers/washu/washuluad.py
cptac/cancers/washu/washuov.py
cptac/cancers/washu/washupdac.py
cptac/cancers/washu/washuucec.py
cptac/tools/__init__.py
cptac/tools/dataframe_tools.py
cptac/tools/download_tools.py
cptac/utils/__init__.py
cptac-1.5.14.dist-info/LICENSE.md
cptac-1.5.14.dist-info/METADATA
cptac-1.5.14.dist-info/WHEEL
cptac-1.5.14.dist-info/top_level.txt
cptac-1.5.14.dist-info/RECORD
