Metadata-Version: 2.1
Name: cptac
Version: 1.5.14
Summary: Python packaging for CPTAC data
Home-page: http://github.com/PayneLab/cptac
Author: Dr. Samuel Payne
Author-email: sam_payne@byu.edu
License: Apache 2.0
Project-URL: Documentation, https://paynelab.github.io/cptac/
Keywords: bioinformatics cancer proteomics genomics open science open data
Classifier: Development Status :: 5 - Production/Stable
Classifier: Intended Audience :: Science/Research
Classifier: Topic :: Scientific/Engineering :: Bio-Informatics
Classifier: License :: OSI Approved :: Apache Software License
Requires-Python: >=3.6
License-File: LICENSE.md
Requires-Dist: numpy (>=1.16.3)
Requires-Dist: pandas (>=1.5.3)
Requires-Dist: requests (>=2.21.0)
Requires-Dist: scipy (>=1.10.0)
Requires-Dist: openpyxl (>=2.6.0)
Requires-Dist: statsmodels (>=0.10.0)
Requires-Dist: pyranges (>=0.0.111)
Requires-Dist: tqdm (>=4.65.0)
